{
    "base_dir": "nlp_bot_engine/data/converted_docs",
    "integrated_data_dir": "nlp_bot_engine/data/integrated_data",
    "technical_data_dir": "nlp_bot_engine/data/extracted_data/technical",
    "compatibility_data_dir": "nlp_bot_engine/data/extracted_data/compatibility",
    "article_data_dir": "nlp_bot_engine/data/extracted_data/artikel",
    "max_workers": 20,
    "theme": "dark",
    "font_size": 12,
    "bot_settings": {
        "response_template_tech": "# Tekniska specifikationer för {product_name}\n\n**Artikelnummer:** {product_id}\n\n{specifications}",
        "response_template_compat": "# Kompatibilitetsinformation för {product_name}\n\n**Artikelnummer:** {product_id}\n\n{compatibility}",
        "response_template_summary": "# {product_name}\n\n**Artikelnummer:** {product_id}\n\n{description}\n\n{specifications}\n\n{compatibility}"
    },
    "supported_file_types": [
        "_pro",
        "_produktblad",
        "_TEK",
        "_sak",
        "_man",
        "_ins",
        "_CERT",
        "_BRO",
        "_INs",
        "_cert",
        "_prodblad",
        "_PRE",
        "_bro",
        "_mdek",
        "_tek",
        "_MAN",
        "_PRO"
    ]
}